LICENSE
MANIFEST.in
README.md
setup.cfg
setup.py
versioneer.py
opsdroid/__init__.py
opsdroid/__main__.py
opsdroid/_version.py
opsdroid/const.py
opsdroid/constraints.py
opsdroid/core.py
opsdroid/events.py
opsdroid/helper.py
opsdroid/loader.py
opsdroid/logging.py
opsdroid/matchers.py
opsdroid/memory.py
opsdroid/message.py
opsdroid/web.py
opsdroid.egg-info/PKG-INFO
opsdroid.egg-info/SOURCES.txt
opsdroid.egg-info/dependency_links.txt
opsdroid.egg-info/entry_points.txt
opsdroid.egg-info/not-zip-safe
opsdroid.egg-info/requires.txt
opsdroid.egg-info/top_level.txt
opsdroid/cli/__init__.py
opsdroid/cli/config.py
opsdroid/cli/logs.py
opsdroid/cli/start.py
opsdroid/cli/utils.py
opsdroid/cli/version.py
opsdroid/cli/tests/test_config.py
opsdroid/configuration/__init__.py
opsdroid/configuration/example_configuration.yaml
opsdroid/configuration/validation.py
opsdroid/connector/__init__.py
opsdroid/connector/facebook/__init__.py
opsdroid/connector/facebook/tests/test_connector_facebook.py
opsdroid/connector/github/__init__.py
opsdroid/connector/github/events.py
opsdroid/connector/github/tests/test_connector_github.py
opsdroid/connector/github/tests/test_private_key.pem
opsdroid/connector/github/tests/github_response_payloads/access_token.json
opsdroid/connector/github/tests/github_response_payloads/bad_credentials.json
opsdroid/connector/github/tests/github_response_payloads/check_completed.json
opsdroid/connector/github/tests/github_response_payloads/check_created.json
opsdroid/connector/github/tests/github_response_payloads/check_failed.json
opsdroid/connector/github/tests/github_response_payloads/check_passed.json
opsdroid/connector/github/tests/github_response_payloads/deployment.json
opsdroid/connector/github/tests/github_response_payloads/installations.json
opsdroid/connector/github/tests/github_response_payloads/issue.json
opsdroid/connector/github/tests/github_response_payloads/issue_close.json
opsdroid/connector/github/tests/github_response_payloads/issue_comment.json
opsdroid/connector/github/tests/github_response_payloads/label.json
opsdroid/connector/github/tests/github_response_payloads/pr.json
opsdroid/connector/github/tests/github_response_payloads/pr_closed.json
